ai_tracker/__init__.py
ai_tracker/cli.py
ai_tracker/config.py
ai_tracker/db.py
ai_tracker/setup.py
ai_tracker/git/__init__.py
ai_tracker/git/install.py
ai_tracker/git/post_commit.py
ai_tracker/hooks/__init__.py
ai_tracker/hooks/capture_before_write.py
ai_tracker/hooks/log_claude_edit.py
ai_tracker/stats/__init__.py
ai_tracker/stats/display.py
ai_tracker/stats/query.py
cc_ai_tracker-0.1.5.dist-info/METADATA
cc_ai_tracker-0.1.5.dist-info/WHEEL
cc_ai_tracker-0.1.5.dist-info/entry_points.txt
cc_ai_tracker-0.1.5.dist-info/RECORD
