Metadata-Version: 2.4
Name: cc-ai-tracker
Version: 0.1.5
Summary: Track AI-generated vs human-made code changes in git repos
Project-URL: Homepage, https://github.com/desplega-ai/ai-toolbox/tree/main/ai-tracker
Project-URL: Repository, https://github.com/desplega-ai/ai-toolbox
Author: desplega-ai
License-Expression: MIT
Keywords: ai,analytics,claude,code-tracking,developer-tools,git
Classifier: Development Status :: 4 - Beta
Classifier: Environment :: Console
Classifier: Intended Audience :: Developers
Classifier: License :: OSI Approved :: MIT License
Classifier: Programming Language :: Python :: 3.11
Classifier: Programming Language :: Python :: 3.12
Classifier: Programming Language :: Python :: 3.13
Classifier: Topic :: Software Development :: Version Control :: Git
Requires-Python: >=3.11
Requires-Dist: click>=8.0.0
Requires-Dist: plotext>=5.0.0
Requires-Dist: rich>=13.0.0
